Metadata-Version: 1.1
Name: nbfi
Version: 0.1.0
Summary: A tiny new brainfuck interpreter in pure python 3
Home-page: https://github.com/Bestoa/py-brainfuck
Author: Besto
Author-email: bestoapache@gmail.com
License: MIT
Keywords: brainfuck
Platform: UNKNOWN
Classifier: Development Status :: 3 - Alpha
Classifier: License :: OSI Approved :: MIT License
Classifier: Programming Language :: Python :: 3
